lu77u_mobilesec/__init__.py
lu77u_mobilesec/__main__.py
lu77u_mobilesec/ai/__init__.py
lu77u_mobilesec/ai/processors/__init__.py
lu77u_mobilesec/ai/processors/batch_processor.py
lu77u_mobilesec/ai/processors/fix_generator.py
lu77u_mobilesec/ai/processors/response_parser.py
lu77u_mobilesec/ai/processors/vulnerability_analyzer.py
lu77u_mobilesec/ai/providers/__init__.py
lu77u_mobilesec/ai/providers/base_provider.py
lu77u_mobilesec/ai/providers/groq_provider.py
lu77u_mobilesec/ai/providers/ollama_provider.py
lu77u_mobilesec/cli/__init__.py
lu77u_mobilesec/cli/app.py
lu77u_mobilesec/cli/arguments.py
lu77u_mobilesec/cli/commands.py
lu77u_mobilesec/cli/interactive.py
lu77u_mobilesec/cli/interface.py
lu77u_mobilesec/constants/__init__.py
lu77u_mobilesec/constants/file_patterns.py
lu77u_mobilesec/constants/frameworks.py
lu77u_mobilesec/constants/severity_levels.py
lu77u_mobilesec/constants/vulnerabilities.py
lu77u_mobilesec/core/__init__.py
lu77u_mobilesec/core/orchestrator.py
lu77u_mobilesec/core/analyzers/__init__.py
lu77u_mobilesec/core/analyzers/flutter_analyzer.py
lu77u_mobilesec/core/analyzers/java_kotlin_analyzer.py
lu77u_mobilesec/core/analyzers/mobsf_analyzer.py
lu77u_mobilesec/core/analyzers/mobsf_analyzer_clean.py
lu77u_mobilesec/core/analyzers/react_native_analyzer.py
lu77u_mobilesec/core/detectors/__init__.py
lu77u_mobilesec/core/detectors/framework_detector.py
lu77u_mobilesec/core/vulnerability/__init__.py
lu77u_mobilesec/core/vulnerability/patterns.py
lu77u_mobilesec/core/vulnerability/reporting.py
lu77u_mobilesec/core/vulnerability/scanner.py
lu77u_mobilesec/core/vulnerability/severity.py
lu77u_mobilesec/system/__init__.py
lu77u_mobilesec/system/doctor/__init__.py
lu77u_mobilesec/system/doctor/main_doctor.py
lu77u_mobilesec/system/validators/__init__.py
lu77u_mobilesec/system/validators/detailed_checker.py
lu77u_mobilesec/system/validators/path_checker.py
lu77u_mobilesec/system/validators/tool_checker.py
lu77u_mobilesec/system/validators/version_checker.py
lu77u_mobilesec-1.0.1.dist-info/licenses/LICENSE
lu77u_mobilesec-1.0.1.dist-info/METADATA
lu77u_mobilesec-1.0.1.dist-info/WHEEL
lu77u_mobilesec-1.0.1.dist-info/entry_points.txt
lu77u_mobilesec-1.0.1.dist-info/top_level.txt
lu77u_mobilesec-1.0.1.dist-info/RECORD
