Metadata-Version: 2.4
Name: lu77U-MobileSec
Version: 1.0.1
Summary: Professional mobile security analysis and vulnerability patching tool for Android applications with AI-powered detection and automated fix generation
Home-page: https://github.com/sam-mg/lu77U-MobileSec
Author: Sam MG Harish (lu77_u)
Author-email: "Sam MG Harish (lu77_u)" <sammgharish@gmail.com>
License-Expression: Apache-2.0
Project-URL: Homepage, https://github.com/sam-mg/lu77U-MobileSec
Project-URL: Repository, https://github.com/sam-mg/lu77U-MobileSec
Project-URL: Issues, https://github.com/sam-mg/lu77U-MobileSec/issues
Project-URL: Documentation, https://github.com/sam-mg/lu77U-MobileSec/wiki
Keywords: mobile-security,apk-analysis,android-security,vulnerability-detection,security-patches,pentesting,mobile-app-security,automated-fixes,lu77U
Classifier: Development Status :: 4 - Beta
Classifier: Intended Audience :: Developers
Classifier: Intended Audience :: Information Technology
Classifier: Topic :: Security
Classifier: Topic :: Software Development :: Testing
Classifier: Topic :: System :: Systems Administration
Classifier: Programming Language :: Python :: 3
Classifier: Programming Language :: Python :: 3.13
Classifier: Operating System :: OS Independent
Classifier: Environment :: Console
Requires-Python: >=3.13
License-File: LICENSE
Requires-Dist: groq>=0.4.0
Requires-Dist: requests>=2.25.0
Requires-Dist: requests-toolbelt>=0.9.1
Requires-Dist: aiohttp>=3.8.0
Requires-Dist: httpx>=0.24.0
Requires-Dist: zipfile36>=0.1.3
Requires-Dist: xmltodict>=0.13.0
Requires-Dist: lxml>=4.9.0
Requires-Dist: jsonschema>=4.0.0
Requires-Dist: pyyaml>=6.0
Requires-Dist: python-magic>=0.4.27
Requires-Dist: psutil>=5.8.0
Requires-Dist: click>=8.0.0
Requires-Dist: rich>=13.0.0
Requires-Dist: colorama>=0.4.6
Requires-Dist: cryptography>=3.4.8
Provides-Extra: dev
Requires-Dist: pytest>=6.0; extra == "dev"
Requires-Dist: pytest-asyncio>=0.18.0; extra == "dev"
Requires-Dist: black>=22.0; extra == "dev"
Requires-Dist: flake8>=4.0; extra == "dev"
Requires-Dist: mypy>=0.950; extra == "dev"
Provides-Extra: analysis
Requires-Dist: beautifulsoup4>=4.9.0; extra == "analysis"
Requires-Dist: lxml>=4.6.0; extra == "analysis"
Requires-Dist: python-magic>=0.4.24; extra == "analysis"
Provides-Extra: full
Requires-Dist: beautifulsoup4>=4.9.0; extra == "full"
Requires-Dist: lxml>=4.6.0; extra == "full"
Requires-Dist: python-magic>=0.4.24; extra == "full"
Requires-Dist: pytest>=6.0; extra == "full"
Requires-Dist: pytest-asyncio>=0.18.0; extra == "full"
Requires-Dist: black>=22.0; extra == "full"
Requires-Dist: flake8>=4.0; extra == "full"
Requires-Dist: mypy>=0.950; extra == "full"
Dynamic: license-file
